page_brute/__init__.py
page_brute/default_signatures.yar
page_brute/page_brute.py
page_brute-1.0.0.dist-info/METADATA
page_brute-1.0.0.dist-info/WHEEL
page_brute-1.0.0.dist-info/entry_points.txt
page_brute-1.0.0.dist-info/top_level.txt
page_brute-1.0.0.dist-info/RECORD
