Metadata-Version: 2.2
Name: page-brute
Version: 1.0.0
Summary: Python 3 Windows Pagefile analysis tool
Author-email: "Corey Forman (digitalsleuth) and Mike Matonis (matonis)" <github@digitalsleuth.ca>
Maintainer-email: "Corey Forman (digitalsleuth)" <github@digitalsleuth.ca>
Project-URL: Homepage, https://github.com/digitalsleuth/page_brute
Keywords: digital forensics,dfir,pagefile,brute
Classifier: Development Status :: 5 - Production/Stable
Classifier: Programming Language :: Python :: 3
Classifier: Operating System :: OS Independent
Requires-Python: >=3.9
Requires-Dist: yara-python
